usha/__init__.py
usha/main.py
usha-0.0.1.dist-info/METADATA
usha-0.0.1.dist-info/WHEEL
usha-0.0.1.dist-info/top_level.txt
usha-0.0.1.dist-info/RECORD
