Metadata-Version: 2.1
Name: usha
Version: 0.0.1
Summary: A secure hashing algorithm
Author: easternblock678
Author-email: 
Keywords: python,hashing,algorithm,secure,hashing algorithm,ultra secure hashing algorithm,usha,usha-2048,secure hashing algorithm,free,ak
Classifier: Development Status :: 1 - Planning
Classifier: Intended Audience :: Developers
Classifier: Programming Language :: Python :: 3
Classifier: Operating System :: Unix
Classifier: Operating System :: MacOS :: MacOS X
Classifier: Operating System :: Microsoft :: Windows
